AssemblyParser/AssemblyParser.py
AssemblyParser/__init__.py
AssemblyParser/__main__.py
AssemblyParser/exceptions.py
AssemblyParser/utilities.py
cs147dvparser-1.4.0.dist-info/LICENSE
cs147dvparser-1.4.0.dist-info/METADATA
cs147dvparser-1.4.0.dist-info/WHEEL
cs147dvparser-1.4.0.dist-info/entry_points.txt
cs147dvparser-1.4.0.dist-info/top_level.txt
cs147dvparser-1.4.0.dist-info/RECORD
