Metadata-Version: 2.1
Name: cs147dvparser
Version: 1.4.0
Summary: converts CS147DV assembly language instructions into hexadecimal code
Home-page: https://rdeamici.github.io/CS147DVParser/
Author: Richard DeAmicis, Jordan Conragan
Author-email: rtdeamicis@gmail.com, jordanvonpordan@gmail.com
License: UNKNOWN
Project-URL: Source, https://github.com/rdeamici/CS147DVParser/tree/master/CS147DVPyParser
Platform: UNKNOWN
Classifier: Programming Language :: Python
Classifier: Programming Language :: Java
Classifier: License :: OSI Approved :: MIT License
Classifier: Operating System :: OS Independent
